jpcovid_v3.py
jpcovid_v3-0.0.1.dist-info/METADATA
jpcovid_v3-0.0.1.dist-info/WHEEL
jpcovid_v3-0.0.1.dist-info/entry_points.txt
jpcovid_v3-0.0.1.dist-info/top_level.txt
jpcovid_v3-0.0.1.dist-info/RECORD
