Metadata-Version: 2.1
Name: jpcovid-v3
Version: 0.0.1
Summary: A package for calculating time transition policy scores against COVID-19 in Japan
Home-page: https://github.com/miyagawa-toshiki/jpcovid_v3
Author: toshiki miyagawa
Author-email: s1922033@stu.musashino-u.ac.jp
License: UNKNOWN
Project-URL: Bug Tracker, https://github.com/miyagawa-toshiki/jpcovid_v3
Platform: UNKNOWN
Classifier: Programming Language :: Python :: 3
Classifier: License :: OSI Approved :: MIT License
Classifier: Operating System :: OS Independent
Requires-Python: >=3.7
